image_batch_converter/__init__.py
image_batch_converter/__main__.py
image_batch_converter/conversion.py
mcpcn_image_batch_converter-1.0.0.dist-info/METADATA
mcpcn_image_batch_converter-1.0.0.dist-info/WHEEL
mcpcn_image_batch_converter-1.0.0.dist-info/entry_points.txt
mcpcn_image_batch_converter-1.0.0.dist-info/licenses/LICENSE
mcpcn_image_batch_converter-1.0.0.dist-info/RECORD
