Metadata-Version: 2.4
Name: mcpcn-image-batch-converter
Version: 1.0.0
Summary: MCP Server for Batch Image Format Conversion
Author: MCP Developer
License: MIT
License-File: LICENSE
Keywords: batch-processing,image-conversion,image-format,mcp
Classifier: Development Status :: 4 - Beta
Classifier: Intended Audience :: Developers
Classifier: License :: OSI Approved :: MIT License
Classifier: Operating System :: OS Independent
Classifier: Programming Language :: Python :: 3
Classifier: Programming Language :: Python :: 3.10
Classifier: Programming Language :: Python :: 3.11
Classifier: Programming Language :: Python :: 3.12
Classifier: Topic :: Multimedia :: Graphics :: Graphics Conversion
Requires-Python: >=3.10
Requires-Dist: mcp>=0.1.0
Requires-Dist: pillow-heif>=0.15.0
Requires-Dist: pillow>=10.0.0
Requires-Dist: pymupdf>=1.24.0
